{"name":"widgets.brease.TableWidget","type":"widget","meta":{"superClass":"widgets.brease.DataHandlerWidget","requires":["widgets.brease.TextInput","widgets.brease.Label","widgets.brease.NumericInput","widgets.brease.CheckBox","widgets.brease.DateTimeInput","widgets.brease.Image","widgets.brease.Rectangle","widgets.brease.DropDownBox","widgets.brease.GenericDialog","widgets.brease.BusyIndicator"],"mixins":[],"parents":["*"],"children":["widgets.brease.TableColumnWidget"],"inheritance":["widgets.brease.TableWidget","widgets.brease.DataHandlerWidget","brease.core.BaseWidget"],"isContainer":"true","visible":"false","filePath":"widgets/brease/TableWidget/TableWidget.js"},"methods":[{"name":"Focus","originalName":"focus","read":false,"description":"Sets focus on the search box or header element, if it can be focused and keyboardOperation=true\n","iatStudioExposed":true},{"name":"GoToFirstPage","originalName":"goToFirstPage","read":false,"description":"\n","iatStudioExposed":true,"result":{"name":"return","type":"Boolean","description":"Navigates to the page given by the value, and returns true or false if it worked respectively failed\n"}},{"name":"GoToLastPage","originalName":"goToLastPage","read":false,"description":"\n","iatStudioExposed":true,"result":{"name":"return","type":"Boolean","description":"Navigates to the page given by the value\n"}},{"name":"GoToNextPage","originalName":"goToNextPage","read":false,"description":"\n","iatStudioExposed":true,"result":{"name":"return","type":"Boolean","description":"Navigates to the page given by the value\n"}},{"name":"GoToPage","originalName":"goToPage","read":false,"description":"\n","iatStudioExposed":true,"parameter":[{"name":"value","type":"Integer","index":0,"description":"\n","optional":false}],"result":{"name":"return","type":"Boolean","description":"Navigates to the page given by the value\n"}},{"name":"GoToPreviousPage","originalName":"goToPreviousPage","read":false,"description":"\n","iatStudioExposed":true,"result":{"name":"return","type":"Boolean","description":"Navigates to the page given by the value\n"}},{"name":"OpenConfiguration","originalName":"openConfiguration","read":false,"description":"Open the filter part of the configuration dialogue\n","iatStudioExposed":true,"parameter":[{"name":"type","type":"MappTableConfigurationType","index":0,"description":"(Supported types: Filtering, Sorting and Styling)\n","optional":false}]},{"name":"setAdditionalStyle","originalName":"setAdditionalStyle","read":false,"description":"Add an additional style to the widget element. The initial style will not be removed.\nThe additional style will not be removed, when the style of the widget is changed.\nYou can remove the additional style via removeAdditionalStyle.\n","iatStudioExposed":false,"parameter":[{"name":"styleName","type":"StyleReference","index":0,"description":"\n","optional":false}]},{"name":"setBusyIndicatorDelay","originalName":"setBusyIndicatorDelay","read":false,"description":"Sets busyIndicatorDelay\n","iatStudioExposed":false,"parameter":[{"name":"busyIndicatorDelay","type":"Integer","index":0,"description":"\n","optional":false}]},{"name":"setEditable","originalName":"setEditable","read":false,"description":"Sets the state of property «editable»\nUsed for «editable» binding; method is called exclusevely by the framework\n","iatStudioExposed":false,"parameter":[{"name":"editable","type":"Boolean","index":0,"description":"\n","optional":false},{"name":"metaData","type":"Object","index":1,"description":"\n","optional":false}]},{"name":"SetEnable","originalName":"setEnable","read":false,"description":"Sets the state of property «enable»\n","iatStudioExposed":true,"parameter":[{"name":"value","type":"Boolean","index":0,"description":"\n","optional":false}]},{"name":"setFilterConfiguration","originalName":"setFilterConfiguration","read":false,"description":"Sets filterConfiguration\n","iatStudioExposed":false,"parameter":[{"name":"filterConfiguration","type":"String","index":0,"description":"\n","optional":false}]},{"name":"setFormat","originalName":"setFormat","read":false,"description":"Sets format\n","iatStudioExposed":false,"parameter":[{"name":"format","type":"String","index":0,"description":"\n","optional":false}]},{"name":"setHeaderHeight","originalName":"setHeaderHeight","read":false,"description":"Sets headerHeaderHeight\n","iatStudioExposed":false,"parameter":[{"name":"headerHeaderHeight","type":"PixelVal","index":0,"description":"\n","optional":false}]},{"name":"setItemsPerPage","originalName":"setItemsPerPage","read":false,"description":"Sets itemsPerPage\n","iatStudioExposed":false,"parameter":[{"name":"itemsPerPage","type":"Integer","index":0,"description":"\n","optional":false}]},{"name":"setNextText","originalName":"setNextText","read":false,"description":"Sets nextText\n","iatStudioExposed":false,"parameter":[{"name":"nextText","type":"String","index":0,"description":"\n","optional":false}]},{"name":"setNextTextKey","originalName":"setNextTextKey","read":false,"description":"set the textkey\n","iatStudioExposed":false,"parameter":[{"name":"key","type":"String","index":0,"description":"The new textkey\n","optional":false}]},{"name":"setPaging","originalName":"setPaging","read":false,"description":"Sets Paging\n","iatStudioExposed":false,"parameter":[{"name":"paging","type":"Boolean","index":0,"description":"\n","optional":false}]},{"name":"setParentCoWiId","originalName":"setParentCoWiId","read":false,"description":"Used to inherit parentCoWiId inside of compound widgets to inner widgets which are not projected, e.g. inner widgets of Login widget\n","iatStudioExposed":false,"parameter":[{"name":"value","type":"String","index":0,"description":"\n","optional":false}]},{"name":"setPreviousText","originalName":"setPreviousText","read":false,"description":"Sets previousText\n","iatStudioExposed":false,"parameter":[{"name":"previousText","type":"String","index":0,"description":"\n","optional":false}]},{"name":"setPreviousTextKey","originalName":"setPreviousTextKey","read":false,"description":"set the textkey\n","iatStudioExposed":false,"parameter":[{"name":"key","type":"String","index":0,"description":"The new textkey\n","optional":false}]},{"name":"setRowHeight","originalName":"setRowHeight","read":false,"description":"Sets rowHeight\n","iatStudioExposed":false,"parameter":[{"name":"rowHeight","type":"String","index":0,"description":"\n","optional":false}]},{"name":"setSearchBox","originalName":"setSearchBox","read":false,"description":"Sets searchBox\n","iatStudioExposed":false,"parameter":[{"name":"searchBox","type":"Boolean","index":0,"description":"\n","optional":false}]},{"name":"setShowPagingButtons","originalName":"setShowPagingButtons","read":false,"description":"Sets ShowPagingButtons\n","iatStudioExposed":false,"parameter":[{"name":"showPagingButtons","type":"Boolean","index":0,"description":"\n","optional":false}]},{"name":"setSortConfiguration","originalName":"setSortConfiguration","read":false,"description":"Sets sortConfiguration\n","iatStudioExposed":false,"parameter":[{"name":"sortConfiguration","type":"String","index":0,"description":"\n","optional":false}]},{"name":"SetStyle","originalName":"setStyle","read":false,"description":"\n","iatStudioExposed":true,"parameter":[{"name":"value","type":"StyleReference","index":0,"description":"\n","optional":false}]},{"name":"setStyleConfiguration","originalName":"setStyleConfiguration","read":false,"description":"Sets styleConfiguration\n","iatStudioExposed":false,"parameter":[{"name":"styleConfiguration","type":"String","index":0,"description":"\n","optional":false}]},{"name":"setTabIndex","originalName":"setTabIndex","read":false,"description":"Sets the state of property «tabIndex»\n","iatStudioExposed":false,"parameter":[{"name":"value","type":"Number","index":0,"description":"\n","optional":false}]},{"name":"SetVisible","originalName":"setVisible","read":false,"description":"Sets the state of property «visible»\n","iatStudioExposed":true,"parameter":[{"name":"value","type":"Boolean","index":0,"description":"\n","optional":false}]},{"name":"ShowTooltip","originalName":"showTooltip","read":false,"description":"\n","iatStudioExposed":true}],"events":[{"name":"Click","description":"Fired when element is clicked on.\n","parameter":[{"name":"origin","type":"String","index":0,"description":"id of widget that triggered this event\n\n\n\n","optional":false},{"name":"horizontalPos","type":"String","index":1,"description":"horizontal position of click in pixel i.e '10px'\n\n\n\n","optional":false},{"name":"verticalPos","type":"String","index":2,"description":"vertical position of click in pixel i.e '10px'\n\n\n\n","optional":false}]},{"name":"CurrentPageNumber","description":"Fires every time there is a page change, updates the Current page, which is currently displayed.\n","parameter":[{"name":"pageNumber","type":"Integer","index":0,"description":"\n","optional":false},{"name":"pageText","type":"String","index":1,"description":"\n","optional":false},{"name":"show","type":"Boolean","index":2,"description":"\n","optional":false},{"name":"select","type":"Integer","index":3,"description":"\n","optional":false},{"name":"pageAlternativeNumber","type":"Integer","index":4,"description":"\n","optional":false},{"name":"pageAlternativeText","type":"String","index":5,"description":"\n","optional":false}]},{"name":"DisabledClick","description":"Fired when disabled element is clicked on.\n","parameter":[{"name":"origin","type":"String","index":0,"description":"id of widget that triggered this event\n\n","optional":false},{"name":"hasPermission","type":"Boolean","index":1,"description":"defines if the state is caused due to missing roles of the current user\n\n","optional":false},{"name":"horizontalPos","type":"String","index":2,"description":"horizontal position of click in pixel i.e '10px'\n\n","optional":false},{"name":"verticalPos","type":"String","index":3,"description":"vertical position of click in pixel i.e '10px'\n\n","optional":false}]},{"name":"EnableChanged","description":"Fired when operability of the widget changes.\n","parameter":[{"name":"value","type":"Boolean","index":0,"description":"operability\n\n\n\n","optional":false}]},{"name":"FirstPageNumber","description":"Fires every time there is a page change, updates the First page.\n","parameter":[{"name":"pageNumber","type":"Integer","index":0,"description":"\n","optional":false},{"name":"pageText","type":"String","index":1,"description":"\n","optional":false},{"name":"show","type":"Boolean","index":2,"description":"\n","optional":false},{"name":"select","type":"Integer","index":3,"description":"\n","optional":false}]},{"name":"LastPageNumber","description":"Fires every time there is a page change, updates the Last page.\n","parameter":[{"name":"pageNumber","type":"Integer","index":0,"description":"\n","optional":false},{"name":"pageText","type":"String","index":1,"description":"\n","optional":false},{"name":"show","type":"Boolean","index":2,"description":"\n","optional":false},{"name":"select","type":"Integer","index":3,"description":"\n","optional":false}]},{"name":"NextPageNumber","description":"Fires every time there is a page change, updates the Next page after the current page.\n","parameter":[{"name":"pageNumber","type":"Integer","index":0,"description":"\n","optional":false},{"name":"pageText","type":"String","index":1,"description":"\n","optional":false},{"name":"show","type":"Boolean","index":2,"description":"\n","optional":false},{"name":"select","type":"Integer","index":3,"description":"\n","optional":false}]},{"name":"OnError","description":"Fired when mapp Component sends an Error.\n","parameter":[{"name":"result","type":"Integer","index":0,"description":"\n","optional":false}]},{"name":"PreviousPageNumber","description":"Fires every time there is a page change, updates the Next page before the current page.\n","parameter":[{"name":"pageNumber","type":"Integer","index":0,"description":"\n","optional":false},{"name":"pageText","type":"String","index":1,"description":"\n","optional":false},{"name":"show","type":"Boolean","index":2,"description":"\n","optional":false},{"name":"select","type":"Integer","index":3,"description":"\n","optional":false}]},{"name":"VisibleChanged","description":"Fired when the visibility of the widget changes.\n","parameter":[{"name":"value","type":"Boolean","index":0,"description":"visibility\n\n\n\n","optional":false}]}],"properties":[{"name":"busyIndicatorDelay","type":"Integer","initOnly":true,"localizable":false,"editableBinding":false,"readOnly":false,"required":false,"owner":"widgets.brease.TableWidget","projectable":true,"description":"delay time for busy indicator [ms]\n","category":"Behavior","defaultValue":"0"},{"name":"enable","type":"Boolean","initOnly":false,"localizable":false,"editableBinding":false,"readOnly":false,"required":false,"owner":"brease.core.BaseWidget","projectable":true,"description":"Initial option to enable widget.\n","category":"Behavior","defaultValue":"true"},{"name":"filterConfiguration","type":"String","initOnly":false,"localizable":false,"editableBinding":false,"readOnly":false,"required":false,"owner":"widgets.brease.TableWidget","projectable":true,"description":"configuration used to set the filter for the alarmlist, predefined structure. Use from the runtime.\n","category":"Data","defaultValue":""},{"name":"format","type":"String","initOnly":false,"localizable":true,"editableBinding":false,"readOnly":false,"required":false,"owner":"widgets.brease.TableWidget","projectable":true,"description":"Specifies the format of the time shown in the input field. This is either a format string (ee.g. \"HH:mm\") or a pattern (\"F\").\n","category":"Appearance","defaultValue":"F"},{"name":"headerHeight","type":"UInteger","initOnly":true,"localizable":false,"editableBinding":false,"readOnly":false,"required":false,"owner":"widgets.brease.TableWidget","projectable":true,"description":"Table header height\n","category":"Appearance","defaultValue":"40"},{"name":"itemsPerPage","type":"Integer","initOnly":true,"localizable":false,"editableBinding":false,"readOnly":false,"required":false,"owner":"widgets.brease.TableWidget","projectable":true,"description":"Sets the number of items per page that will be displayed when paging is enabled\n","category":"Behavior","defaultValue":"3"},{"name":"nextText","type":"String","initOnly":true,"localizable":true,"editableBinding":false,"readOnly":false,"required":false,"owner":"widgets.brease.TableWidget","projectable":true,"description":"Text for the 'Next' button\n","category":"Appearance","defaultValue":"Next"},{"name":"paging","type":"Boolean","initOnly":true,"localizable":false,"editableBinding":false,"readOnly":false,"required":false,"owner":"widgets.brease.TableWidget","projectable":true,"description":"If TRUE, predefined paging will be used\n","category":"Behavior","defaultValue":"true"},{"name":"permissionOperate","type":"RoleCollection","initOnly":true,"localizable":false,"editableBinding":false,"readOnly":false,"required":false,"owner":"brease.core.BaseWidget","projectable":true,"description":"restricts operability to users, which have given roles\n","category":"Accessibility"},{"name":"permissionView","type":"RoleCollection","initOnly":true,"localizable":false,"editableBinding":false,"readOnly":false,"required":false,"owner":"brease.core.BaseWidget","projectable":true,"description":"restricts visibility to users, which have given roles\n","category":"Accessibility"},{"name":"previousText","type":"String","initOnly":true,"localizable":true,"editableBinding":false,"readOnly":false,"required":false,"owner":"widgets.brease.TableWidget","projectable":true,"description":"Text for the 'Previous' button\n","category":"Appearance","defaultValue":"Previous"},{"name":"searchBox","type":"Boolean","initOnly":true,"localizable":false,"editableBinding":false,"readOnly":false,"required":false,"owner":"widgets.brease.TableWidget","projectable":true,"description":"If TRUE, predefined search box will be used\n","category":"Behavior","defaultValue":"true"},{"name":"showPagingButtons","type":"Boolean","initOnly":true,"localizable":false,"editableBinding":false,"readOnly":false,"required":false,"owner":"widgets.brease.TableWidget","projectable":true,"description":"If TRUE, the paging buttons will be shown, else external paging has to be used.\n","category":"Behavior","defaultValue":"true"},{"name":"sortConfiguration","type":"String","initOnly":false,"localizable":false,"editableBinding":false,"readOnly":false,"required":false,"owner":"widgets.brease.TableWidget","projectable":true,"description":"configuration used to set the filter for the alarmlist, predefined structure. Use from the runtime.\n","category":"Data","defaultValue":""},{"name":"style","type":"StyleReference","initOnly":false,"localizable":false,"editableBinding":false,"readOnly":false,"required":false,"owner":"brease.core.BaseWidget","projectable":true,"description":"reference to a style for this widget type\n","category":"Appearance","defaultValue":"default"},{"name":"styleConfiguration","type":"String","initOnly":false,"localizable":false,"editableBinding":false,"readOnly":false,"required":false,"owner":"widgets.brease.TableWidget","projectable":true,"description":"configuration used to set the filter for the alarmlist, predefined structure. Use from the runtime.\n","category":"Data","defaultValue":""},{"name":"tabIndex","type":"Integer","initOnly":true,"localizable":false,"editableBinding":false,"readOnly":false,"required":false,"owner":"brease.core.BaseWidget","projectable":true,"description":"sets if a widget should have autofocus enabled (0), the order of the focus (>0),\nor if autofocus should be disabled (-1)\n","category":"Behavior","defaultValue":"-1"},{"name":"tooltip","type":"String","initOnly":true,"localizable":true,"editableBinding":false,"readOnly":false,"required":false,"owner":"brease.core.BaseWidget","projectable":true,"description":"reference to a tooltip for a widget\n","category":"Appearance","defaultValue":""},{"name":"visible","type":"Boolean","initOnly":false,"localizable":false,"editableBinding":false,"readOnly":false,"required":false,"owner":"brease.core.BaseWidget","projectable":true,"description":"change visibility\n","category":"Behavior","defaultValue":"true"},{"name":"rowHeight","type":"Size","defaultValue":"0","description":"Sets a uniform rowHeight of the widget.","initOnly":true,"required":false,"readOnly":false,"projectable":true,"hide":false,"cssProp":true},{"name":"maxHeight","type":"Size","defaultValue":"0","description":"maximum outer height of widget","initOnly":true,"required":false,"readOnly":false,"projectable":true,"hide":false,"cssProp":true},{"name":"minHeight","type":"Size","defaultValue":"0","description":"minimum outer height of widget","initOnly":true,"required":false,"readOnly":false,"projectable":true,"hide":false,"cssProp":true},{"name":"maxWidth","type":"Size","defaultValue":"0","description":"maximum outer width of widget","initOnly":true,"required":false,"readOnly":false,"projectable":true,"hide":false,"cssProp":true},{"name":"minWidth","type":"Size","defaultValue":"0","description":"minimum outer width of widget","initOnly":true,"required":false,"readOnly":false,"projectable":true,"hide":false,"cssProp":true},{"name":"zIndex","type":"UInteger","description":"The zIndex property specifies the z-order of a widget and its childs.<br/>\r\n        When widgets overlap, z-order determines which one covers the other. A widget with a larger zIndex generally covers a widget with a lower one.<br/>\r\n        The zIndex must be unique within a content.<br/>","initOnly":true,"required":true,"readOnly":false,"projectable":true,"owner":"brease.core.BaseWidget","hide":false,"cssProp":true},{"name":"left","type":"Integer","description":"absolute position measured from left boundary of parent container","initOnly":true,"required":false,"readOnly":false,"projectable":true,"owner":"brease.core.BaseWidget","hide":false,"cssProp":true},{"name":"top","type":"Integer","description":"absolute position measured from top boundary of parent container","initOnly":true,"required":false,"readOnly":false,"projectable":true,"owner":"brease.core.BaseWidget","hide":false,"cssProp":true},{"name":"height","type":"Size","defaultValue":"300","description":"outer height of widget","initOnly":true,"required":false,"readOnly":false,"projectable":true,"owner":"widgets.brease.TableWidget","hide":false,"cssProp":true},{"name":"width","type":"Size","defaultValue":"600","description":"outer width of widget","initOnly":true,"required":false,"readOnly":false,"projectable":true,"owner":"widgets.brease.TableWidget","hide":false,"cssProp":true}],"dependencies":{"files":["widgets/brease/DataHandlerWidget/DataHandlerWidget.js","brease/events/EventDispatcher.js","brease/events/BreaseEvent.js","brease/enum/Enum.js","widgets/brease/TableWidget/libs/Renderer.js","widgets/brease/TableWidget/libs/Controller.js","widgets/brease/TableWidget/libs/Model.js","widgets/brease/TableWidget/libs/FocusHandler.js","brease/decorators/CultureDependency.js","brease/decorators/MeasurementSystemDependency.js","brease/decorators/VisibilityDependency.js","widgets/brease/TableWidget/libs/ConfigBuilder.js","widgets/brease/common/BusyIndicatorHandler/libs/BusyIndicatorHandler.js","widgets/brease/common/libs/BreaseResizeObserver.js","brease/decorators/ContentActivatedDependency.js","widgets/brease/TextInput/TextInput.js","widgets/brease/Label/Label.js","widgets/brease/NumericInput/NumericInput.js","widgets/brease/CheckBox/CheckBox.js","widgets/brease/DateTimeInput/DateTimeInput.js","widgets/brease/Image/Image.js","widgets/brease/Rectangle/Rectangle.js","widgets/brease/DropDownBox/DropDownBox.js","widgets/brease/GenericDialog/GenericDialog.js","widgets/brease/BusyIndicator/BusyIndicator.js"],"widgets":["widgets/brease/TableWidget/TableWidget.js","widgets/brease/DataHandlerWidget/DataHandlerWidget.js","widgets/brease/TextInput/TextInput.js","widgets/brease/Label/Label.js","widgets/brease/NumericInput/NumericInput.js","widgets/brease/CheckBox/CheckBox.js","widgets/brease/DateTimeInput/DateTimeInput.js","widgets/brease/Image/Image.js","widgets/brease/Rectangle/Rectangle.js","widgets/brease/DropDownBox/DropDownBox.js","widgets/brease/GenericDialog/GenericDialog.js","widgets/brease/BusyIndicator/BusyIndicator.js"]},"categories":{"Category":["Data"]},"descriptions":{"short":"Superclass for Alarmlist and other table dependent Mapp connected widgets, not to be shown in Automation Studio","de":"Superclass for Alarmlist and other table dependent Mapp connected widgets, not to be shown in Automation Studio","en":"Superclass for Alarmlist and other table dependent Mapp connected widgets, not to be shown in Automation Studio"},"superproperties":{"id":{"type":"WidgetId"},"enable":{"type":"Boolean"},"permissionOperate":{"type":"RoleCollection"},"permissionView":{"type":"RoleCollection"},"style":{"type":"StyleReference"},"tabIndex":{"type":"Integer"},"tooltip":{"type":"String"},"visible":{"type":"Boolean"},"zIndex":{"type":"UInteger"},"left":{"type":"Integer"},"top":{"type":"Integer"},"height":{"type":"AutoSize"},"width":{"type":"AutoSize"}},"styleproperties":{"StyleProperty":[{"$":{"name":"width","type":"Size","not_styleable":"true","owner":"widgets.brease.TableWidget","category":"Layout","groupRefId":"Size","groupOrder":"1","default":"600"},"StyleElement":[{"$":{"attribute":"@include elemWidth($value)"}}],"Description":["outer width of widget"]},{"$":{"name":"height","type":"Size","not_styleable":"true","owner":"widgets.brease.TableWidget","category":"Layout","groupRefId":"Size","groupOrder":"2","default":"300"},"StyleElement":[{"$":{"attribute":"@include elemHeight($value)"}}],"Description":["outer height of widget"]},{"$":{"name":"top","type":"Integer","not_styleable":"true","owner":"brease.core.BaseWidget","category":"Layout","groupRefId":"Position","groupOrder":"1"},"StyleElement":[{"$":{"attribute":"@include elemTop($value)"}}],"Description":["absolute position measured from top boundary of parent container"]},{"$":{"name":"left","type":"Integer","not_styleable":"true","owner":"brease.core.BaseWidget","category":"Layout","groupRefId":"Position","groupOrder":"2"},"StyleElement":[{"$":{"attribute":"@include elemLeft($value)"}}],"Description":["absolute position measured from left boundary of parent container"]},{"$":{"name":"zIndex","type":"UInteger","not_styleable":"true","owner":"brease.core.BaseWidget","category":"Layout","required":"true"},"StyleElement":[{"$":{"attribute":"z-index"}}],"Description":["The zIndex property specifies the z-order of a widget and its childs.<br/>\r\n        When widgets overlap, z-order determines which one covers the other. A widget with a larger zIndex generally covers a widget with a lower one.<br/>\r\n        The zIndex must be unique within a content.<br/>"]},{"$":{"name":"minWidth","type":"Size","not_styleable":"true","default":"0","category":"Layout","groupRefId":"Size","groupOrder":"3"},"StyleElement":[{"$":{"attribute":"@include elemMinWidth($value)"}}],"Description":["minimum outer width of widget"]},{"$":{"name":"maxWidth","type":"Size","not_styleable":"true","default":"0","category":"Layout","groupRefId":"Size","groupOrder":"4"},"StyleElement":[{"$":{"attribute":"@include elemMaxWidth($value)"}}],"Description":["maximum outer width of widget"]},{"$":{"name":"minHeight","type":"Size","not_styleable":"true","default":"0","category":"Layout","groupRefId":"Size","groupOrder":"5"},"StyleElement":[{"$":{"attribute":"@include elemMinHeight($value)"}}],"Description":["minimum outer height of widget"]},{"$":{"name":"maxHeight","type":"Size","not_styleable":"true","default":"0","category":"Layout","groupRefId":"Size","groupOrder":"6"},"StyleElement":[{"$":{"attribute":"@include elemMaxHeight($value)"}}],"Description":["maximum outer height of widget"]},{"$":{"name":"rowHeight","type":"Size","category":"Appearance","not_styleable":"true","default":"0"},"StyleElement":[{"$":{"selector":"&.breaseTableWidget .tw_table table tbody tr","attribute":"@include rowHeight($value)"}},{"$":{"selector":"&.breaseTableWidget .tw_table table tbody tr img","attribute":"@include rowHeight($value)"}},{"$":{"selector":"&.breaseTableWidget #fakeRowHeight","attribute":"@include rowHeight($value)"}}],"Description":["Sets a uniform rowHeight of the widget."]},{"$":{"name":"borderStyle","type":"BorderStyle","category":"Appearance","default":"none"},"StyleElement":[{"$":{"selector":"&.breaseTableWidget","attribute":"border-style"}}],"Description":["Widget border style"]},{"$":{"name":"borderWidth","type":"PixelValCollection","category":"Appearance","default":"1px"},"StyleElement":[{"$":{"selector":"&.breaseTableWidget","attribute":"border-width"}}],"Description":["Widget border width"]},{"$":{"name":"borderColor","type":"ColorCollection","category":"Appearance","default":"#ddd"},"StyleElement":[{"$":{"selector":"&.breaseTableWidget","attribute":"border-color"}}],"Description":["Widget border color"]},{"$":{"name":"backColor","type":"Color","category":"Appearance","default":"transparent"},"StyleElement":[{"$":{"selector":"&.breaseTableWidget","attribute":"background-color"}}],"Description":["Widget border color background color"]},{"$":{"name":"headerBackColor","type":"Color","category":"Appearance","groupRefId":"Header","groupOrder":"1","default":"#fff"},"StyleElement":[{"$":{"selector":"&.breaseTableWidget .breaseTableColumnWidget:not(.disabled)","attribute":"background-color"}}],"Description":["Sets the backColor of the header"]},{"$":{"name":"headerBackGroundGradient","type":"Gradient","category":"Appearance","groupRefId":"Header","groupOrder":"1","default":""},"StyleElement":[{"$":{"selector":"&.breaseTableWidget .breaseTableColumnWidget:not(.disabled)","attribute":"@include backGroundGradient('$value')"}}],"Description":["Sets the background gradient of the header"]},{"$":{"name":"headerTextColor","type":"Color","category":"Appearance","groupRefId":"Header","groupOrder":"2","default":"#000"},"StyleElement":[{"$":{"selector":"&.breaseTableWidget .breaseTableColumnWidget:not(.disabled)","attribute":"color"}}],"Description":["Sets the header text color"]},{"$":{"name":"headerFontSize","type":"PixelVal","category":"Font","groupRefId":"Header","groupOrder":"3","default":"16px"},"StyleElement":[{"$":{"selector":"&.breaseTableWidget .breaseTableColumnWidget .headerText","attribute":"font-size"}}],"Description":["Fontsize of the header texts"]},{"$":{"name":"backColorSelectedRow","type":"Color","category":"Appearance","groupRefId":"Rows","groupOrder":"3","default":"#ff8800"},"StyleElement":[{"$":{"selector":"&.breaseTableWidget .dataTable tr.selected td","attribute":"background-color"}},{"$":{"selector":"&.breaseTableWidget .dataTable paginate_button current","attribute":"border-color"}}],"Description":["Backcolor of selected list entries"]},{"$":{"name":"mouseDownBackColor","type":"Color","category":"Appearance","groupRefId":"Rows","groupOrder":"3","default":"transparent"},"StyleElement":[{"$":{"selector":"&.breaseTableWidget .dataTable tr.mousedown:not(.selected) td","attribute":"@include active-background-color-important($value)"}}],"Description":["Backcolor of the mouse down triggered on an entry"]},{"$":{"name":"backColorEvenRow","type":"Color","category":"Appearance","groupRefId":"Rows","groupOrder":"1","default":"#fff"},"StyleElement":[{"$":{"selector":"&.breaseTableWidget .dataTable tr:not(.disabled):nth-of-type(even)","attribute":"background-color"}}],"Description":["Backcolor of even list entries"]},{"$":{"name":"backColorOddRow","type":"Color","category":"Appearance","groupRefId":"Rows","groupOrder":"2","default":"#f9f9f9"},"StyleElement":[{"$":{"selector":"&.breaseTableWidget .dataTable tr:not(.disabled):nth-of-type(odd)","attribute":"background-color"}}],"Description":["Backcolor of odd list entries"]},{"$":{"name":"mouseDownTextColor","type":"Color","category":"Appearance","groupRefId":"Rows","groupOrder":"4","default":"transparent"},"StyleElement":[{"$":{"selector":"&.breaseTableWidget .dataTable>tbody>tr.mousedown:not(.selected) td","attribute":"@include active-color($value)"}}],"Description":["Text color of an entry which the mouse down is triggered at"]},{"$":{"name":"textColorSelectedRow","type":"Color","category":"Appearance","groupRefId":"Rows","groupOrder":"4","default":"#fff"},"StyleElement":[{"$":{"selector":"&.breaseTableWidget .dataTable>tbody>tr.selected td","attribute":"color"}}],"Description":["Text color of selected list entries"]},{"$":{"name":"textColor","type":"Color","category":"Appearance","groupRefId":"Rows","groupOrder":"5","default":"#000"},"StyleElement":[{"$":{"selector":"&.breaseTableWidget .dataTable>tbody>tr:not(.selected):not(.disabled)>td","attribute":"color"}}],"Description":["Text color of list entries"]},{"$":{"name":"fontSize","type":"PixelVal","category":"Font","groupRefId":"Rows","groupOrder":"6","default":"14px"},"StyleElement":[{"$":{"selector":"&.breaseTableWidget .dataTable>tbody>tr>td","attribute":"font-size"}}],"Description":["Fontsize of list entries"]},{"$":{"name":"fontName","category":"Font","type":"FontName","default":"Arial"},"StyleElement":[{"$":{"selector":"&.breaseTableWidget .breaseTableColumnWidget","attribute":"font-family"}},{"$":{"selector":"&.breaseTableWidget .dataTable>tbody>tr>td","attribute":"font-family"}}],"Description":["Fontname of the text"]},{"$":{"name":"sortingButtonColor","category":"Appearance","type":"Color","default":"#ececec"},"StyleElement":[{"$":{"selector":"svg > g > path.unselected","attribute":"fill"}}],"Description":["Color of the arrow that is not the sorted way"]},{"$":{"name":"sortingButtonActiveColor","category":"Appearance","type":"Color","default":"#5f8dd3"},"StyleElement":[{"$":{"selector":"svg > g > path.selected","attribute":"fill"}}],"Description":["Color of the arrow that is the sorted way"]},{"$":{"name":"shadow","type":"Shadow","category":"Appearance","default":"none"},"StyleElement":[{"$":{"attribute":"@include box-shadow($value)"}}],"Description":["Shadow of the Widget"]},{"$":{"name":"cornerRadius","type":"PixelValCollection","category":"Appearance","default":"0px"},"StyleElement":[{"$":{"attribute":"@include border-radius($value)"}}],"Description":["Sets the radius of the widget rounded corners. For further information, please see its type"]},{"$":{"name":"headerBold","type":"Boolean","default":"true","category":"Font"},"StyleElement":[{"$":{"selector":"&.breaseTableWidget .breaseTableColumnWidget","attribute":"@include font-weight-bold($value)"}}],"Description":["If true, the font style of the header is bold"]},{"$":{"name":"headerItalic","type":"Boolean","default":"false","category":"Font"},"StyleElement":[{"$":{"selector":"&.breaseTableWidget .breaseTableColumnWidget","attribute":"@include font-style-italic($value)"}}],"Description":["If true, the font style of the header is italic"]},{"$":{"name":"headerTextAlign","type":"brease.enum.TextAlign","default":"left","category":"Appearance"},"StyleElement":[{"$":{"selector":"&.breaseTableWidget .breaseTableColumnWidget > .headerText","attribute":"@include text-alignment($value)"}}],"Description":["Alignment of the text in a cell"]},{"$":{"name":"headerCellPadding","category":"Appearance","type":"Padding","default":"0px 8px"},"StyleElement":[{"$":{"selector":"&.breaseTableWidget .breaseTableColumnWidget > .headerText","attribute":"padding"}}],"Description":["Sets the padding of the header cell. For further information, please see its type"]},{"$":{"name":"headerCellBorderColor","type":"Color","category":"Appearance","default":"#DDDDDD"},"StyleElement":[{"$":{"selector":"&.breaseTableWidget .breaseTableColumnWidget","attribute":"border-color"}}],"Description":["Sets the border color of the header. For further information, please see its type"]},{"$":{"name":"headerCellBorderWidth","type":"PixelValCollection","category":"Appearance","default":"1px"},"StyleElement":[{"$":{"selector":"&.breaseTableWidget .breaseTableColumnWidget","attribute":"border-width"}}],"Description":["Sets the border width of each cell. For further information, please see its type"]},{"$":{"name":"headerCellBorderStyle","type":"BorderStyle","category":"Appearance","default":"none"},"StyleElement":[{"$":{"selector":"&.breaseTableWidget .breaseTableColumnWidget","attribute":"border-bottom-style"}},{"$":{"selector":"&.breaseTableWidget .breaseTableColumnWidget","attribute":"border-right-style"}},{"$":{"selector":"&.breaseTableWidget .breaseTableColumnWidget","attribute":"border-top-style"}},{"$":{"selector":"&.breaseTableWidget .breaseTableColumnWidget","attribute":"border-left-style"}}],"Description":["Sets the border style of the header. For further information, please see its type"]},{"$":{"name":"bold","type":"Boolean","default":"false","category":"Font"},"StyleElement":[{"$":{"selector":"&.breaseTableWidget .tw_table table tbody tr td","attribute":"@include font-weight-bold($value)"}}],"Description":["If true, the font style of the table is bold"]},{"$":{"name":"italic","type":"Boolean","default":"false","category":"Font"},"StyleElement":[{"$":{"selector":"&.breaseTableWidget .tw_table table tbody tr td","attribute":"@include font-style-italic($value)"}}],"Description":["If true, the font style of the table is italic"]},{"$":{"name":"textAlign","type":"brease.enum.TextAlign","default":"left","category":"Appearance"},"StyleElement":[{"$":{"selector":"&.breaseTableWidget .tw_table table tbody tr td","attribute":"@include text-alignment($value)"}}],"Description":["Alignment of the text in a cell"]},{"$":{"name":"cellBorderColor","type":"Color","category":"Appearance","default":"#DDDDDD"},"StyleElement":[{"$":{"selector":"&.breaseTableWidget .tw_table table tbody tr td","attribute":"border-color"}}],"Description":["Sets the border color of the header. For further information, please see its type"]},{"$":{"name":"cellBorderWidth","type":"PixelValCollection","category":"Appearance","default":"1px 0px 0px 0px"},"StyleElement":[{"$":{"selector":"&.breaseTableWidget .tw_table table tbody tr td","attribute":"border-width"}}],"Description":["Sets the border width of each cell. For further information, please see its type"]},{"$":{"name":"cellBorderStyle","type":"BorderStyle","category":"Appearance","default":"solid"},"StyleElement":[{"$":{"selector":"&.breaseTableWidget .tw_table table tbody tr td","attribute":"border-bottom-style"}},{"$":{"selector":"&.breaseTableWidget .tw_table table tbody tr td","attribute":"border-right-style"}},{"$":{"selector":"&.breaseTableWidget .tw_table table tbody tr td","attribute":"border-top-style"}},{"$":{"selector":"&.breaseTableWidget .tw_table table tbody tr td","attribute":"border-left-style"}}],"Description":["Sets the border style of the header. For further information, please see its type"]},{"$":{"name":"cellPadding","category":"Appearance","type":"Padding","default":"8px 14px"},"StyleElement":[{"$":{"selector":"&.breaseTableWidget .tw_table table tbody tr td","attribute":"padding"}}],"Description":["Sets the padding of the header cell. For further information, please see its type"]},{"$":{"name":"backGroundGradient","type":"Gradient","category":"Appearance","default":""},"StyleElement":[{"$":{"selector":"&:not(.disabled)","attribute":"@include backGroundGradient('$value')"}}],"Description":["Background as a gradient"]},{"$":{"name":"opacity","type":"Opacity","category":"Appearance","default":"1"},"StyleElement":[{"$":{"attribute":"opacity"}}],"Description":["Opacity of the widget"]},{"$":{"name":"disabledBackColorEvenRow","type":"Color","category":"Appearance","groupRefId":"Rows","groupOrder":"1","default":"#EAEAEA"},"StyleElement":[{"$":{"selector":"&.breaseTableWidget .dataTable tr:nth-of-type(even).disabled","attribute":"background-color"}}],"Description":["Backcolor of even list entries"]},{"$":{"name":"disabledBackColorOddRow","type":"Color","category":"Appearance","groupRefId":"Rows","groupOrder":"2","default":"#FFFFFF"},"StyleElement":[{"$":{"selector":"&.breaseTableWidget .dataTable tr:nth-of-type(odd).disabled","attribute":"background-color"}}],"Description":["Backcolor of odd list entries"]},{"$":{"name":"disabledHeaderBackColor","type":"Color","category":"Appearance","groupRefId":"Header","groupOrder":"1","default":"#FCFCFC"},"StyleElement":[{"$":{"selector":".breaseTableColumnWidget.disabled","attribute":"background-color"}}],"Description":["Sets the backColor of the header"]},{"$":{"name":"disabledHeaderTextColor","type":"Color","category":"Appearance","groupRefId":"Header","groupOrder":"2","default":"#C8C8C8"},"StyleElement":[{"$":{"selector":".breaseTableColumnWidget.disabled > .headerText","attribute":"color"}}],"Description":["Sets the header text color"]},{"$":{"name":"disabledTextColor","type":"Color","category":"Appearance","groupRefId":"Rows","groupOrder":"5","default":"#C8C8C8"},"StyleElement":[{"$":{"selector":"&.breaseTableWidget .dataTable>tbody>tr.disabled>td","attribute":"color"}}],"Description":["Text color of list entries"]}],"$":{}},"propertygroups":{"PropertyGroup":[{"$":{"name":"Size","type":"String","category":"Layout"},"Description":["outer height and width of widget"]},{"$":{"name":"Position","type":"String","category":"Layout"},"Description":["top and left of widget"]}]}}